keye_vl_utils/__init__.py
keye_vl_utils/vision_process.py
keye_vl_utils-1.5.2.dist-info/METADATA
keye_vl_utils-1.5.2.dist-info/WHEEL
keye_vl_utils-1.5.2.dist-info/RECORD
