Metadata-Version: 2.4
Name: keye-vl-utils
Version: 1.5.2
Summary: Keye Vision Language Model Utils - PyTorch
Project-URL: Homepage, https://github.com/Kwai-Keye/Keye/tree/main/keye-vl-utils
Project-URL: Repository, https://github.com/Kwai-Keye/Keye.git
Project-URL: Issues, https://github.com/Kwai-Keye/Keye/issues
Author: Kwai Keye Team
License: Apache-2.0
Keywords: keye-vl,large language model,pytorch,vision language model
Classifier: Development Status :: 4 - Beta
Classifier: License :: OSI Approved :: Apache Software License
Classifier: Programming Language :: Python :: 3
Classifier: Topic :: Scientific/Engineering :: Artificial Intelligence
Requires-Python: >=3.8
Requires-Dist: av
Requires-Dist: packaging
Requires-Dist: pillow
Requires-Dist: requests
Provides-Extra: decord
Requires-Dist: decord; extra == 'decord'
